{"stats":{"minecraft:killed":{"minecraft:warden":1},"minecraft:crafted":{"videobotmod:metal_detector":1},"minecraft:custom":{"minecraft:time_since_rest":40630,"minecraft:walk_under_water_one_cm":357,"minecraft:crouch_one_cm":6,"minecraft:play_time":40630,"minecraft:walk_one_cm":4056,"minecraft:sneak_time":843,"minecraft:mob_kills":1,"minecraft:boat_one_cm":1588,"minecraft:drop":1,"minecraft:jump":31,"minecraft:leave_game":1,"minecraft:damage_dealt":5011,"minecraft:walk_on_water_one_cm":1082,"minecraft:time_since_death":40630,"minecraft:total_world_time":49380,"minecraft:interact_with_crafting_table":1,"minecraft:fly_one_cm":103206},"minecraft:dropped":{"minecraft:piston":1},"minecraft:picked_up":{"minecraft:repeater":4,"minecraft:lever":1,"minecraft:bone_meal":1,"minecraft:redstone_torch":1,"minecraft:redstone":18,"minecraft:cod":1,"minecraft:piston":1,"minecraft:sculk_catalyst":1},"minecraft:used":{"minecraft:bamboo_raft":1,"minecraft:redstone_torch":10,"minecraft:debug_stick":36,"minecraft:sticky_piston":20,"minecraft:bedrock":18,"minecraft:light_gray_wool":3,"minecraft:white_wool":129,"minecraft:lever":3,"minecraft:ender_eye":14,"minecraft:black_wool":27,"minecraft:repeater":10,"minecraft:sand":20,"minecraft:red_wool":30,"minecraft:redstone":38,"minecraft:slime_block":13,"minecraft:sculk_shrieker":1,"minecraft:end_portal_frame":16,"minecraft:redstone_block":12,"minecraft:obsidian":21,"minecraft:netherite_sword":106}},"DataVersion":3465}